[
    {
        "m17_0": 77,
        "m17_1": 74,
        "m17_2": 80
    },
    {
        "m17_0": 11,
        "m17_1": 99,
        "m17_2": 81
    },
    {
        "m17_0": 65,
        "m17_1": 79,
        "m17_2": 123
    },
    {
        "m17_0": 61,
        "m17_1": 78,
        "m17_2": 75
    },
    {
        "m17_0": 47,
        "m17_1": 181,
        "m17_2": 111
    },
    {
        "m17_0": 63,
        "m17_1": 75,
        "m17_2": 106
    },
    {
        "m17_0": 34,
        "m17_1": 78,
        "m17_2": 75
    },
    {
        "m17_0": 40,
        "m17_1": 85,
        "m17_2": 71
    },
    {
        "m17_0": 74,
        "m17_1": 92,
        "m17_2": 74
    },
    {
        "m17_0": 53,
        "m17_1": 48,
        "m17_2": 85
    },
    {
        "m17_0": 12,
        "m17_1": 8,
        "m17_2": 41
    },
    {
        "m17_0": 159,
        "m17_1": 179,
        "m17_2": 246
    },
    {
        "m17_0": 46,
        "m17_1": 102,
        "m17_2": 105
    },
    {
        "m17_0": 97,
        "m17_1": 139,
        "m17_2": 191
    },
    {
        "m17_0": 6,
        "m17_1": 6,
        "m17_2": 10
    },
    {
        "m17_0": 173,
        "m17_1": 157,
        "m17_2": 78
    },
    {
        "m17_0": 80,
        "m17_1": 109,
        "m17_2": 68
    },
    {
        "m17_0": 81,
        "m17_1": 126,
        "m17_2": 206
    },
    {
        "m17_0": 66,
        "m17_1": 109,
        "m17_2": 194
    },
    {
        "m17_0": 35,
        "m17_1": 42,
        "m17_2": 36
    },
    {
        "m17_0": 68,
        "m17_1": 79,
        "m17_2": 73
    },
    {
        "m17_0": 30,
        "m17_1": 152,
        "m17_2": 154
    },
    {
        "m17_0": 42,
        "m17_1": 75,
        "m17_2": 29
    },
    {
        "m17_0": 71,
        "m17_1": 58,
        "m17_2": 54
    },
    {
        "m17_0": 40,
        "m17_1": 46,
        "m17_2": 58
    },
    {
        "m17_0": 33,
        "m17_1": 68,
        "m17_2": 161
    },
    {
        "m17_0": 60,
        "m17_1": 125,
        "m17_2": 92
    },
    {
        "m17_0": 27,
        "m17_1": 88,
        "m17_2": 74
    },
    {
        "m17_0": 58,
        "m17_1": 82,
        "m17_2": 121
    },
    {
        "m17_0": 51,
        "m17_1": 181,
        "m17_2": 150
    },
    {
        "m17_0": 73,
        "m17_1": 86,
        "m17_2": 137
    },
    {
        "m17_0": 68,
        "m17_1": 122,
        "m17_2": 136
    },
    {
        "m17_0": 66,
        "m17_1": 78,
        "m17_2": 68
    },
    {
        "m17_0": 16,
        "m17_1": 48,
        "m17_2": 147
    },
    {
        "m17_0": 46,
        "m17_1": 79,
        "m17_2": 69
    },
    {
        "m17_0": 8,
        "m17_1": 6,
        "m17_2": 23
    },
    {
        "m17_0": 78,
        "m17_1": 116,
        "m17_2": 180
    },
    {
        "m17_0": 111,
        "m17_1": 149,
        "m17_2": 157
    },
    {
        "m17_0": 14,
        "m17_1": 14,
        "m17_2": 28
    },
    {
        "m17_0": 31,
        "m17_1": 45,
        "m17_2": 43
    },
    {
        "m17_0": 44,
        "m17_1": 86,
        "m17_2": 80
    },
    {
        "m17_0": 86,
        "m17_1": 107,
        "m17_2": 75
    },
    {
        "m17_0": 5,
        "m17_1": 5,
        "m17_2": 7
    },
    {
        "m17_0": 23,
        "m17_1": 38,
        "m17_2": 36
    },
    {
        "m17_0": 80,
        "m17_1": 198,
        "m17_2": 197
    },
    {
        "m17_0": 118,
        "m17_1": 184,
        "m17_2": 153
    },
    {
        "m17_0": 29,
        "m17_1": 33,
        "m17_2": 64
    },
    {
        "m17_0": 6,
        "m17_1": 5,
        "m17_2": 17
    },
    {
        "m17_0": 56,
        "m17_1": 78,
        "m17_2": 83
    },
    {
        "m17_0": 144,
        "m17_1": 191,
        "m17_2": 223
    },
    {
        "m17_0": 34,
        "m17_1": 81,
        "m17_2": 62
    },
    {
        "m17_0": 112,
        "m17_1": 202,
        "m17_2": 236
    },
    {
        "m17_0": 58,
        "m17_1": 67,
        "m17_2": 109
    },
    {
        "m17_0": 114,
        "m17_1": 125,
        "m17_2": 163
    },
    {
        "m17_0": 32,
        "m17_1": 87,
        "m17_2": 78
    },
    {
        "m17_0": 23,
        "m17_1": 46,
        "m17_2": 52
    },
    {
        "m17_0": 73,
        "m17_1": 150,
        "m17_2": 149
    },
    {
        "m17_0": 125,
        "m17_1": 177,
        "m17_2": 247
    },
    {
        "m17_0": 63,
        "m17_1": 173,
        "m17_2": 189
    },
    {
        "m17_0": 23,
        "m17_1": 20,
        "m17_2": 22
    },
    {
        "m17_0": 39,
        "m17_1": 42,
        "m17_2": 59
    },
    {
        "m17_0": 65,
        "m17_1": 90,
        "m17_2": 143
    },
    {
        "m17_0": 81,
        "m17_1": 86,
        "m17_2": 107
    },
    {
        "m17_0": 89,
        "m17_1": 53,
        "m17_2": 122
    },
    {
        "m17_0": 85,
        "m17_1": 66,
        "m17_2": 141
    },
    {
        "m17_0": 68,
        "m17_1": 91,
        "m17_2": 162
    },
    {
        "m17_0": 82,
        "m17_1": 111,
        "m17_2": 172
    },
    {
        "m17_0": 57,
        "m17_1": 68,
        "m17_2": 111
    },
    {
        "m17_0": 77,
        "m17_1": 141,
        "m17_2": 201
    },
    {
        "m17_0": 104,
        "m17_1": 145,
        "m17_2": 233
    },
    {
        "m17_0": 103,
        "m17_1": 185,
        "m17_2": 238
    },
    {
        "m17_0": 13,
        "m17_1": 13,
        "m17_2": 14
    },
    {
        "m17_0": 115,
        "m17_1": 148,
        "m17_2": 204
    },
    {
        "m17_0": 28,
        "m17_1": 67,
        "m17_2": 63
    },
    {
        "m17_0": 18,
        "m17_1": 34,
        "m17_2": 32
    },
    {
        "m17_0": 84,
        "m17_1": 114,
        "m17_2": 110
    },
    {
        "m17_0": 35,
        "m17_1": 52,
        "m17_2": 96
    },
    {
        "m17_0": 34,
        "m17_1": 43,
        "m17_2": 57
    },
    {
        "m17_0": 15,
        "m17_1": 31,
        "m17_2": 71
    },
    {
        "m17_0": 89,
        "m17_1": 124,
        "m17_2": 204
    },
    {
        "m17_0": 74,
        "m17_1": 148,
        "m17_2": 221
    },
    {
        "m17_0": 27,
        "m17_1": 49,
        "m17_2": 27
    },
    {
        "m17_0": 13,
        "m17_1": 14,
        "m17_2": 17
    },
    {
        "m17_0": 24,
        "m17_1": 19,
        "m17_2": 18
    },
    {
        "m17_0": 33,
        "m17_1": 27,
        "m17_2": 33
    },
    {
        "m17_0": 40,
        "m17_1": 52,
        "m17_2": 118
    },
    {
        "m17_0": 42,
        "m17_1": 164,
        "m17_2": 182
    },
    {
        "m17_0": 40,
        "m17_1": 29,
        "m17_2": 60
    },
    {
        "m17_0": 10,
        "m17_1": 10,
        "m17_2": 30
    },
    {
        "m17_0": 42,
        "m17_1": 46,
        "m17_2": 54
    },
    {
        "m17_0": 113,
        "m17_1": 153,
        "m17_2": 165
    },
    {
        "m17_0": 67,
        "m17_1": 124,
        "m17_2": 156
    },
    {
        "m17_0": 88,
        "m17_1": 102,
        "m17_2": 183
    },
    {
        "m17_0": 66,
        "m17_1": 83,
        "m17_2": 106
    },
    {
        "m17_0": 46,
        "m17_1": 75,
        "m17_2": 75
    },
    {
        "m17_0": 2,
        "m17_1": 2,
        "m17_2": 228
    },
    {
        "m17_0": 16,
        "m17_1": 15,
        "m17_2": 24
    },
    {
        "m17_0": 8,
        "m17_1": 7,
        "m17_2": 11
    },
    {
        "m17_0": 73,
        "m17_1": 145,
        "m17_2": 170
    },
    {
        "m17_0": 85,
        "m17_1": 113,
        "m17_2": 216
    },
    {
        "m17_0": 97,
        "m17_1": 186,
        "m17_2": 242
    },
    {
        "m17_0": 44,
        "m17_1": 63,
        "m17_2": 75
    },
    {
        "m17_0": 42,
        "m17_1": 97,
        "m17_2": 60
    },
    {
        "m17_0": 107,
        "m17_1": 229,
        "m17_2": 243
    },
    {
        "m17_0": 5,
        "m17_1": 4,
        "m17_2": 10
    },
    {
        "m17_0": 13,
        "m17_1": 48,
        "m17_2": 77
    },
    {
        "m17_0": 33,
        "m17_1": 28,
        "m17_2": 60
    },
    {
        "m17_0": 61,
        "m17_1": 66,
        "m17_2": 89
    },
    {
        "m17_0": 25,
        "m17_1": 28,
        "m17_2": 30
    },
    {
        "m17_0": 9,
        "m17_1": 9,
        "m17_2": 13
    },
    {
        "m17_0": 49,
        "m17_1": 89,
        "m17_2": 120
    },
    {
        "m17_0": 43,
        "m17_1": 51,
        "m17_2": 100
    },
    {
        "m17_0": 76,
        "m17_1": 101,
        "m17_2": 142
    },
    {
        "m17_0": 59,
        "m17_1": 110,
        "m17_2": 171
    },
    {
        "m17_0": 62,
        "m17_1": 105,
        "m17_2": 120
    },
    {
        "m17_0": 66,
        "m17_1": 119,
        "m17_2": 136
    },
    {
        "m17_0": 89,
        "m17_1": 95,
        "m17_2": 218
    },
    {
        "m17_0": 30,
        "m17_1": 86,
        "m17_2": 77
    },
    {
        "m17_0": 59,
        "m17_1": 118,
        "m17_2": 119
    },
    {
        "m17_0": 33,
        "m17_1": 71,
        "m17_2": 62
    },
    {
        "m17_0": 49,
        "m17_1": 84,
        "m17_2": 89
    },
    {
        "m17_0": 140,
        "m17_1": 190,
        "m17_2": 179
    },
    {
        "m17_0": 7,
        "m17_1": 5,
        "m17_2": 23
    },
    {
        "m17_0": 11,
        "m17_1": 9,
        "m17_2": 17
    },
    {
        "m17_0": 156,
        "m17_1": 115,
        "m17_2": 207
    },
    {
        "m17_0": 2,
        "m17_1": 4,
        "m17_2": 5
    },
    {
        "m17_0": 26,
        "m17_1": 36,
        "m17_2": 36
    },
    {
        "m17_0": 83,
        "m17_1": 129,
        "m17_2": 123
    },
    {
        "m17_0": 37,
        "m17_1": 113,
        "m17_2": 148
    },
    {
        "m17_0": 51,
        "m17_1": 110,
        "m17_2": 144
    },
    {
        "m17_0": 37,
        "m17_1": 63,
        "m17_2": 80
    },
    {
        "m17_0": 1,
        "m17_1": 1,
        "m17_2": 207
    },
    {
        "m17_0": 68,
        "m17_1": 108,
        "m17_2": 99
    },
    {
        "m17_0": 58,
        "m17_1": 204,
        "m17_2": 226
    },
    {
        "m17_0": 37,
        "m17_1": 59,
        "m17_2": 67
    },
    {
        "m17_0": 25,
        "m17_1": 57,
        "m17_2": 60
    },
    {
        "m17_0": 86,
        "m17_1": 162,
        "m17_2": 222
    },
    {
        "m17_0": 34,
        "m17_1": 68,
        "m17_2": 153
    },
    {
        "m17_0": 87,
        "m17_1": 140,
        "m17_2": 98
    },
    {
        "m17_0": 23,
        "m17_1": 23,
        "m17_2": 82
    },
    {
        "m17_0": 43,
        "m17_1": 46,
        "m17_2": 75
    },
    {
        "m17_0": 7,
        "m17_1": 8,
        "m17_2": 24
    },
    {
        "m17_0": 49,
        "m17_1": 58,
        "m17_2": 63
    },
    {
        "m17_0": 59,
        "m17_1": 87,
        "m17_2": 164
    },
    {
        "m17_0": 79,
        "m17_1": 157,
        "m17_2": 154
    },
    {
        "m17_0": 85,
        "m17_1": 179,
        "m17_2": 238
    },
    {
        "m17_0": 44,
        "m17_1": 40,
        "m17_2": 59
    },
    {
        "m17_0": 96,
        "m17_1": 142,
        "m17_2": 235
    },
    {
        "m17_0": 41,
        "m17_1": 75,
        "m17_2": 70
    },
    {
        "m17_0": 128,
        "m17_1": 149,
        "m17_2": 84
    },
    {
        "m17_0": 34,
        "m17_1": 37,
        "m17_2": 56
    },
    {
        "m17_0": 6,
        "m17_1": 6,
        "m17_2": 7
    },
    {
        "m17_0": 5,
        "m17_1": 5,
        "m17_2": 11
    },
    {
        "m17_0": 42,
        "m17_1": 207,
        "m17_2": 174
    },
    {
        "m17_0": 41,
        "m17_1": 40,
        "m17_2": 40
    },
    {
        "m17_0": 88,
        "m17_1": 118,
        "m17_2": 111
    },
    {
        "m17_0": 97,
        "m17_1": 165,
        "m17_2": 113
    },
    {
        "m17_0": 20,
        "m17_1": 13,
        "m17_2": 35
    },
    {
        "m17_0": 2,
        "m17_1": 2,
        "m17_2": 3
    },
    {
        "m17_0": 42,
        "m17_1": 38,
        "m17_2": 46
    },
    {
        "m17_0": 77,
        "m17_1": 94,
        "m17_2": 97
    },
    {
        "m17_0": 2,
        "m17_1": 2,
        "m17_2": 7
    },
    {
        "m17_0": 59,
        "m17_1": 62,
        "m17_2": 77
    },
    {
        "m17_0": 16,
        "m17_1": 16,
        "m17_2": 19
    },
    {
        "m17_0": 95,
        "m17_1": 166,
        "m17_2": 196
    },
    {
        "m17_0": 20,
        "m17_1": 71,
        "m17_2": 90
    },
    {
        "m17_0": 85,
        "m17_1": 75,
        "m17_2": 180
    },
    {
        "m17_0": 118,
        "m17_1": 150,
        "m17_2": 101
    },
    {
        "m17_0": 38,
        "m17_1": 27,
        "m17_2": 101
    },
    {
        "m17_0": 30,
        "m17_1": 45,
        "m17_2": 48
    },
    {
        "m17_0": 63,
        "m17_1": 88,
        "m17_2": 126
    },
    {
        "m17_0": 3,
        "m17_1": 3,
        "m17_2": 40
    },
    {
        "m17_0": 83,
        "m17_1": 134,
        "m17_2": 243
    },
    {
        "m17_0": 57,
        "m17_1": 113,
        "m17_2": 112
    },
    {
        "m17_0": 107,
        "m17_1": 169,
        "m17_2": 132
    },
    {
        "m17_0": 90,
        "m17_1": 148,
        "m17_2": 195
    },
    {
        "m17_0": 67,
        "m17_1": 148,
        "m17_2": 213
    },
    {
        "m17_0": 24,
        "m17_1": 30,
        "m17_2": 48
    },
    {
        "m17_0": 5,
        "m17_1": 5,
        "m17_2": 7
    },
    {
        "m17_0": 72,
        "m17_1": 130,
        "m17_2": 87
    },
    {
        "m17_0": 48,
        "m17_1": 129,
        "m17_2": 136
    },
    {
        "m17_0": 96,
        "m17_1": 198,
        "m17_2": 205
    },
    {
        "m17_0": 34,
        "m17_1": 16,
        "m17_2": 42
    },
    {
        "m17_0": 69,
        "m17_1": 116,
        "m17_2": 126
    },
    {
        "m17_0": 43,
        "m17_1": 55,
        "m17_2": 78
    },
    {
        "m17_0": 65,
        "m17_1": 98,
        "m17_2": 111
    },
    {
        "m17_0": 111,
        "m17_1": 124,
        "m17_2": 184
    },
    {
        "m17_0": 32,
        "m17_1": 74,
        "m17_2": 57
    },
    {
        "m17_0": 83,
        "m17_1": 136,
        "m17_2": 214
    },
    {
        "m17_0": 66,
        "m17_1": 174,
        "m17_2": 214
    },
    {
        "m17_0": 33,
        "m17_1": 65,
        "m17_2": 70
    },
    {
        "m17_0": 28,
        "m17_1": 21,
        "m17_2": 48
    },
    {
        "m17_0": 151,
        "m17_1": 167,
        "m17_2": 252
    },
    {
        "m17_0": 50,
        "m17_1": 55,
        "m17_2": 89
    },
    {
        "m17_0": 59,
        "m17_1": 97,
        "m17_2": 119
    },
    {
        "m17_0": 75,
        "m17_1": 112,
        "m17_2": 191
    },
    {
        "m17_0": 73,
        "m17_1": 95,
        "m17_2": 105
    },
    {
        "m17_0": 11,
        "m17_1": 14,
        "m17_2": 29
    },
    {
        "m17_0": 84,
        "m17_1": 154,
        "m17_2": 213
    },
    {
        "m17_0": 45,
        "m17_1": 53,
        "m17_2": 66
    },
    {
        "m17_0": 39,
        "m17_1": 44,
        "m17_2": 85
    },
    {
        "m17_0": 42,
        "m17_1": 153,
        "m17_2": 154
    },
    {
        "m17_0": 107,
        "m17_1": 181,
        "m17_2": 196
    },
    {
        "m17_0": 101,
        "m17_1": 176,
        "m17_2": 221
    },
    {
        "m17_0": 84,
        "m17_1": 87,
        "m17_2": 167
    },
    {
        "m17_0": 71,
        "m17_1": 148,
        "m17_2": 145
    },
    {
        "m17_0": 142,
        "m17_1": 149,
        "m17_2": 180
    },
    {
        "m17_0": 77,
        "m17_1": 78,
        "m17_2": 175
    },
    {
        "m17_0": 81,
        "m17_1": 204,
        "m17_2": 119
    },
    {
        "m17_0": 40,
        "m17_1": 45,
        "m17_2": 33
    },
    {
        "m17_0": 64,
        "m17_1": 78,
        "m17_2": 84
    },
    {
        "m17_0": 42,
        "m17_1": 216,
        "m17_2": 90
    },
    {
        "m17_0": 23,
        "m17_1": 27,
        "m17_2": 30
    },
    {
        "m17_0": 17,
        "m17_1": 11,
        "m17_2": 11
    },
    {
        "m17_0": 89,
        "m17_1": 157,
        "m17_2": 198
    },
    {
        "m17_0": 64,
        "m17_1": 183,
        "m17_2": 154
    },
    {
        "m17_0": 84,
        "m17_1": 234,
        "m17_2": 253
    },
    {
        "m17_0": 96,
        "m17_1": 110,
        "m17_2": 194
    },
    {
        "m17_0": 35,
        "m17_1": 49,
        "m17_2": 47
    },
    {
        "m17_0": 65,
        "m17_1": 99,
        "m17_2": 246
    },
    {
        "m17_0": 18,
        "m17_1": 28,
        "m17_2": 73
    },
    {
        "m17_0": 10,
        "m17_1": 11,
        "m17_2": 9
    },
    {
        "m17_0": 63,
        "m17_1": 86,
        "m17_2": 140
    },
    {
        "m17_0": 50,
        "m17_1": 78,
        "m17_2": 91
    },
    {
        "m17_0": 39,
        "m17_1": 72,
        "m17_2": 83
    },
    {
        "m17_0": 8,
        "m17_1": 10,
        "m17_2": 22
    },
    {
        "m17_0": 4,
        "m17_1": 7,
        "m17_2": 15
    },
    {
        "m17_0": 4,
        "m17_1": 4,
        "m17_2": 19
    },
    {
        "m17_0": 70,
        "m17_1": 65,
        "m17_2": 124
    },
    {
        "m17_0": 88,
        "m17_1": 132,
        "m17_2": 185
    },
    {
        "m17_0": 84,
        "m17_1": 155,
        "m17_2": 152
    },
    {
        "m17_0": 45,
        "m17_1": 23,
        "m17_2": 25
    },
    {
        "m17_0": 75,
        "m17_1": 70,
        "m17_2": 176
    },
    {
        "m17_0": 67,
        "m17_1": 73,
        "m17_2": 111
    },
    {
        "m17_0": 30,
        "m17_1": 43,
        "m17_2": 35
    },
    {
        "m17_0": 55,
        "m17_1": 133,
        "m17_2": 168
    },
    {
        "m17_0": 62,
        "m17_1": 103,
        "m17_2": 150
    },
    {
        "m17_0": 48,
        "m17_1": 40,
        "m17_2": 58
    },
    {
        "m17_0": 57,
        "m17_1": 60,
        "m17_2": 84
    },
    {
        "m17_0": 105,
        "m17_1": 144,
        "m17_2": 256
    },
    {
        "m17_0": 128,
        "m17_1": 165,
        "m17_2": 242
    },
    {
        "m17_0": 70,
        "m17_1": 66,
        "m17_2": 122
    },
    {
        "m17_0": 30,
        "m17_1": 31,
        "m17_2": 34
    },
    {
        "m17_0": 27,
        "m17_1": 75,
        "m17_2": 73
    },
    {
        "m17_0": 38,
        "m17_1": 54,
        "m17_2": 41
    },
    {
        "m17_0": 65,
        "m17_1": 131,
        "m17_2": 190
    },
    {
        "m17_0": 104,
        "m17_1": 193,
        "m17_2": 105
    },
    {
        "m17_0": 72,
        "m17_1": 145,
        "m17_2": 168
    },
    {
        "m17_0": 76,
        "m17_1": 196,
        "m17_2": 194
    },
    {
        "m17_0": 77,
        "m17_1": 41,
        "m17_2": 87
    },
    {
        "m17_0": 57,
        "m17_1": 126,
        "m17_2": 190
    },
    {
        "m17_0": 8,
        "m17_1": 10,
        "m17_2": 18
    },
    {
        "m17_0": 91,
        "m17_1": 176,
        "m17_2": 169
    },
    {
        "m17_0": 43,
        "m17_1": 29,
        "m17_2": 44
    },
    {
        "m17_0": 69,
        "m17_1": 62,
        "m17_2": 151
    },
    {
        "m17_0": 34,
        "m17_1": 52,
        "m17_2": 99
    },
    {
        "m17_0": 55,
        "m17_1": 96,
        "m17_2": 97
    },
    {
        "m17_0": 83,
        "m17_1": 98,
        "m17_2": 159
    },
    {
        "m17_0": 7,
        "m17_1": 4,
        "m17_2": 26
    },
    {
        "m17_0": 26,
        "m17_1": 21,
        "m17_2": 49
    },
    {
        "m17_0": 19,
        "m17_1": 22,
        "m17_2": 35
    },
    {
        "m17_0": 16,
        "m17_1": 29,
        "m17_2": 33
    },
    {
        "m17_0": 69,
        "m17_1": 135,
        "m17_2": 107
    },
    {
        "m17_0": 48,
        "m17_1": 47,
        "m17_2": 81
    },
    {
        "m17_0": 18,
        "m17_1": 19,
        "m17_2": 23
    },
    {
        "m17_0": 57,
        "m17_1": 174,
        "m17_2": 190
    },
    {
        "m17_0": 19,
        "m17_1": 13,
        "m17_2": 21
    },
    {
        "m17_0": 85,
        "m17_1": 97,
        "m17_2": 81
    },
    {
        "m17_0": 32,
        "m17_1": 33,
        "m17_2": 49
    },
    {
        "m17_0": 69,
        "m17_1": 134,
        "m17_2": 204
    },
    {
        "m17_0": 32,
        "m17_1": 59,
        "m17_2": 45
    },
    {
        "m17_0": 33,
        "m17_1": 93,
        "m17_2": 77
    },
    {
        "m17_0": 16,
        "m17_1": 15,
        "m17_2": 22
    },
    {
        "m17_0": 99,
        "m17_1": 162,
        "m17_2": 219
    },
    {
        "m17_0": 50,
        "m17_1": 128,
        "m17_2": 147
    },
    {
        "m17_0": 103,
        "m17_1": 140,
        "m17_2": 247
    },
    {
        "m17_0": 72,
        "m17_1": 57,
        "m17_2": 76
    },
    {
        "m17_0": 101,
        "m17_1": 182,
        "m17_2": 186
    },
    {
        "m17_0": 49,
        "m17_1": 58,
        "m17_2": 67
    },
    {
        "m17_0": 62,
        "m17_1": 134,
        "m17_2": 163
    },
    {
        "m17_0": 88,
        "m17_1": 201,
        "m17_2": 167
    },
    {
        "m17_0": 81,
        "m17_1": 159,
        "m17_2": 196
    },
    {
        "m17_0": 62,
        "m17_1": 95,
        "m17_2": 93
    },
    {
        "m17_0": 60,
        "m17_1": 110,
        "m17_2": 119
    },
    {
        "m17_0": 22,
        "m17_1": 18,
        "m17_2": 47
    },
    {
        "m17_0": 26,
        "m17_1": 32,
        "m17_2": 41
    },
    {
        "m17_0": 75,
        "m17_1": 127,
        "m17_2": 119
    },
    {
        "m17_0": 31,
        "m17_1": 48,
        "m17_2": 49
    },
    {
        "m17_0": 78,
        "m17_1": 145,
        "m17_2": 228
    },
    {
        "m17_0": 72,
        "m17_1": 123,
        "m17_2": 103
    },
    {
        "m17_0": 68,
        "m17_1": 145,
        "m17_2": 104
    },
    {
        "m17_0": 45,
        "m17_1": 48,
        "m17_2": 67
    },
    {
        "m17_0": 89,
        "m17_1": 183,
        "m17_2": 175
    },
    {
        "m17_0": 128,
        "m17_1": 124,
        "m17_2": 128
    },
    {
        "m17_0": 41,
        "m17_1": 68,
        "m17_2": 73
    },
    {
        "m17_0": 14,
        "m17_1": 20,
        "m17_2": 17
    },
    {
        "m17_0": 28,
        "m17_1": 84,
        "m17_2": 95
    },
    {
        "m17_0": 51,
        "m17_1": 74,
        "m17_2": 90
    },
    {
        "m17_0": 12,
        "m17_1": 13,
        "m17_2": 17
    },
    {
        "m17_0": 148,
        "m17_1": 218,
        "m17_2": 124
    },
    {
        "m17_0": 79,
        "m17_1": 94,
        "m17_2": 197
    },
    {
        "m17_0": 5,
        "m17_1": 5,
        "m17_2": 18
    },
    {
        "m17_0": 6,
        "m17_1": 7,
        "m17_2": 15
    },
    {
        "m17_0": 64,
        "m17_1": 72,
        "m17_2": 79
    },
    {
        "m17_0": 58,
        "m17_1": 55,
        "m17_2": 164
    },
    {
        "m17_0": 7,
        "m17_1": 6,
        "m17_2": 12
    },
    {
        "m17_0": 44,
        "m17_1": 65,
        "m17_2": 63
    },
    {
        "m17_0": 80,
        "m17_1": 116,
        "m17_2": 174
    },
    {
        "m17_0": 62,
        "m17_1": 92,
        "m17_2": 123
    },
    {
        "m17_0": 63,
        "m17_1": 208,
        "m17_2": 140
    },
    {
        "m17_0": 83,
        "m17_1": 93,
        "m17_2": 63
    },
    {
        "m17_0": 74,
        "m17_1": 69,
        "m17_2": 117
    },
    {
        "m17_0": 68,
        "m17_1": 169,
        "m17_2": 236
    },
    {
        "m17_0": 47,
        "m17_1": 58,
        "m17_2": 121
    },
    {
        "m17_0": 129,
        "m17_1": 211,
        "m17_2": 81
    },
    {
        "m17_0": 31,
        "m17_1": 70,
        "m17_2": 124
    },
    {
        "m17_0": 115,
        "m17_1": 144,
        "m17_2": 206
    },
    {
        "m17_0": 60,
        "m17_1": 112,
        "m17_2": 111
    },
    {
        "m17_0": 33,
        "m17_1": 24,
        "m17_2": 30
    },
    {
        "m17_0": 33,
        "m17_1": 53,
        "m17_2": 105
    },
    {
        "m17_0": 5,
        "m17_1": 5,
        "m17_2": 13
    },
    {
        "m17_0": 64,
        "m17_1": 123,
        "m17_2": 222
    },
    {
        "m17_0": 2,
        "m17_1": 2,
        "m17_2": 5
    },
    {
        "m17_0": 79,
        "m17_1": 101,
        "m17_2": 184
    },
    {
        "m17_0": 51,
        "m17_1": 99,
        "m17_2": 213
    },
    {
        "m17_0": 2,
        "m17_1": 3,
        "m17_2": 2
    },
    {
        "m17_0": 73,
        "m17_1": 151,
        "m17_2": 177
    },
    {
        "m17_0": 4,
        "m17_1": 4,
        "m17_2": 38
    },
    {
        "m17_0": 87,
        "m17_1": 168,
        "m17_2": 251
    },
    {
        "m17_0": 47,
        "m17_1": 74,
        "m17_2": 79
    },
    {
        "m17_0": 3,
        "m17_1": 4,
        "m17_2": 5
    },
    {
        "m17_0": 19,
        "m17_1": 11,
        "m17_2": 43
    },
    {
        "m17_0": 144,
        "m17_1": 204,
        "m17_2": 200
    },
    {
        "m17_0": 13,
        "m17_1": 16,
        "m17_2": 25
    },
    {
        "m17_0": 19,
        "m17_1": 28,
        "m17_2": 49
    },
    {
        "m17_0": 100,
        "m17_1": 109,
        "m17_2": 148
    },
    {
        "m17_0": 172,
        "m17_1": 232,
        "m17_2": 256
    },
    {
        "m17_0": 5,
        "m17_1": 4,
        "m17_2": 5
    },
    {
        "m17_0": 60,
        "m17_1": 186,
        "m17_2": 117
    },
    {
        "m17_0": 93,
        "m17_1": 188,
        "m17_2": 111
    },
    {
        "m17_0": 93,
        "m17_1": 150,
        "m17_2": 154
    },
    {
        "m17_0": 44,
        "m17_1": 110,
        "m17_2": 134
    },
    {
        "m17_0": 67,
        "m17_1": 140,
        "m17_2": 165
    },
    {
        "m17_0": 30,
        "m17_1": 22,
        "m17_2": 49
    },
    {
        "m17_0": 66,
        "m17_1": 222,
        "m17_2": 254
    },
    {
        "m17_0": 64,
        "m17_1": 87,
        "m17_2": 88
    },
    {
        "m17_0": 40,
        "m17_1": 24,
        "m17_2": 44
    },
    {
        "m17_0": 11,
        "m17_1": 5,
        "m17_2": 8
    },
    {
        "m17_0": 22,
        "m17_1": 23,
        "m17_2": 44
    },
    {
        "m17_0": 12,
        "m17_1": 4,
        "m17_2": 11
    },
    {
        "m17_0": 20,
        "m17_1": 65,
        "m17_2": 62
    },
    {
        "m17_0": 28,
        "m17_1": 51,
        "m17_2": 27
    },
    {
        "m17_0": 7,
        "m17_1": 9,
        "m17_2": 11
    },
    {
        "m17_0": 58,
        "m17_1": 93,
        "m17_2": 146
    },
    {
        "m17_0": 74,
        "m17_1": 67,
        "m17_2": 88
    },
    {
        "m17_0": 13,
        "m17_1": 15,
        "m17_2": 10
    },
    {
        "m17_0": 36,
        "m17_1": 81,
        "m17_2": 35
    },
    {
        "m17_0": 65,
        "m17_1": 83,
        "m17_2": 132
    },
    {
        "m17_0": 59,
        "m17_1": 110,
        "m17_2": 109
    },
    {
        "m17_0": 14,
        "m17_1": 14,
        "m17_2": 14
    },
    {
        "m17_0": 47,
        "m17_1": 72,
        "m17_2": 55
    },
    {
        "m17_0": 115,
        "m17_1": 134,
        "m17_2": 226
    },
    {
        "m17_0": 43,
        "m17_1": 114,
        "m17_2": 178
    },
    {
        "m17_0": 37,
        "m17_1": 144,
        "m17_2": 143
    },
    {
        "m17_0": 65,
        "m17_1": 125,
        "m17_2": 178
    },
    {
        "m17_0": 74,
        "m17_1": 89,
        "m17_2": 160
    },
    {
        "m17_0": 35,
        "m17_1": 44,
        "m17_2": 69
    },
    {
        "m17_0": 108,
        "m17_1": 154,
        "m17_2": 161
    },
    {
        "m17_0": 35,
        "m17_1": 184,
        "m17_2": 43
    },
    {
        "m17_0": 24,
        "m17_1": 28,
        "m17_2": 25
    },
    {
        "m17_0": 54,
        "m17_1": 115,
        "m17_2": 125
    },
    {
        "m17_0": 56,
        "m17_1": 86,
        "m17_2": 162
    },
    {
        "m17_0": 49,
        "m17_1": 103,
        "m17_2": 187
    },
    {
        "m17_0": 28,
        "m17_1": 62,
        "m17_2": 90
    },
    {
        "m17_0": 54,
        "m17_1": 54,
        "m17_2": 73
    },
    {
        "m17_0": 58,
        "m17_1": 69,
        "m17_2": 84
    },
    {
        "m17_0": 84,
        "m17_1": 179,
        "m17_2": 173
    },
    {
        "m17_0": 51,
        "m17_1": 71,
        "m17_2": 91
    },
    {
        "m17_0": 1,
        "m17_1": 1,
        "m17_2": 4
    },
    {
        "m17_0": 14,
        "m17_1": 18,
        "m17_2": 22
    },
    {
        "m17_0": 31,
        "m17_1": 26,
        "m17_2": 31
    },
    {
        "m17_0": 10,
        "m17_1": 6,
        "m17_2": 10
    },
    {
        "m17_0": 3,
        "m17_1": 2,
        "m17_2": 24
    },
    {
        "m17_0": 64,
        "m17_1": 135,
        "m17_2": 133
    },
    {
        "m17_0": 72,
        "m17_1": 120,
        "m17_2": 182
    },
    {
        "m17_0": 31,
        "m17_1": 57,
        "m17_2": 15
    },
    {
        "m17_0": 97,
        "m17_1": 111,
        "m17_2": 140
    },
    {
        "m17_0": 92,
        "m17_1": 101,
        "m17_2": 141
    },
    {
        "m17_0": 52,
        "m17_1": 73,
        "m17_2": 89
    },
    {
        "m17_0": 8,
        "m17_1": 10,
        "m17_2": 17
    },
    {
        "m17_0": 62,
        "m17_1": 116,
        "m17_2": 180
    },
    {
        "m17_0": 34,
        "m17_1": 35,
        "m17_2": 45
    },
    {
        "m17_0": 85,
        "m17_1": 147,
        "m17_2": 234
    },
    {
        "m17_0": 59,
        "m17_1": 36,
        "m17_2": 66
    },
    {
        "m17_0": 40,
        "m17_1": 84,
        "m17_2": 78
    },
    {
        "m17_0": 26,
        "m17_1": 20,
        "m17_2": 28
    },
    {
        "m17_0": 71,
        "m17_1": 60,
        "m17_2": 85
    },
    {
        "m17_0": 20,
        "m17_1": 15,
        "m17_2": 30
    },
    {
        "m17_0": 34,
        "m17_1": 25,
        "m17_2": 37
    },
    {
        "m17_0": 115,
        "m17_1": 143,
        "m17_2": 184
    },
    {
        "m17_0": 25,
        "m17_1": 30,
        "m17_2": 39
    },
    {
        "m17_0": 26,
        "m17_1": 15,
        "m17_2": 35
    },
    {
        "m17_0": 11,
        "m17_1": 14,
        "m17_2": 21
    },
    {
        "m17_0": 30,
        "m17_1": 31,
        "m17_2": 60
    },
    {
        "m17_0": 21,
        "m17_1": 9,
        "m17_2": 69
    },
    {
        "m17_0": 62,
        "m17_1": 102,
        "m17_2": 159
    },
    {
        "m17_0": 72,
        "m17_1": 159,
        "m17_2": 200
    },
    {
        "m17_0": 66,
        "m17_1": 111,
        "m17_2": 152
    },
    {
        "m17_0": 96,
        "m17_1": 170,
        "m17_2": 215
    },
    {
        "m17_0": 102,
        "m17_1": 154,
        "m17_2": 250
    },
    {
        "m17_0": 10,
        "m17_1": 17,
        "m17_2": 10
    },
    {
        "m17_0": 34,
        "m17_1": 52,
        "m17_2": 43
    },
    {
        "m17_0": 82,
        "m17_1": 142,
        "m17_2": 164
    },
    {
        "m17_0": 30,
        "m17_1": 30,
        "m17_2": 77
    },
    {
        "m17_0": 52,
        "m17_1": 144,
        "m17_2": 128
    },
    {
        "m17_0": 46,
        "m17_1": 40,
        "m17_2": 145
    },
    {
        "m17_0": 102,
        "m17_1": 129,
        "m17_2": 233
    },
    {
        "m17_0": 95,
        "m17_1": 71,
        "m17_2": 119
    },
    {
        "m17_0": 159,
        "m17_1": 197,
        "m17_2": 239
    },
    {
        "m17_0": 15,
        "m17_1": 14,
        "m17_2": 13
    },
    {
        "m17_0": 5,
        "m17_1": 6,
        "m17_2": 11
    },
    {
        "m17_0": 149,
        "m17_1": 200,
        "m17_2": 236
    },
    {
        "m17_0": 49,
        "m17_1": 141,
        "m17_2": 78
    },
    {
        "m17_0": 67,
        "m17_1": 173,
        "m17_2": 214
    },
    {
        "m17_0": 16,
        "m17_1": 25,
        "m17_2": 9
    },
    {
        "m17_0": 35,
        "m17_1": 68,
        "m17_2": 72
    },
    {
        "m17_0": 23,
        "m17_1": 19,
        "m17_2": 89
    }
]
